discoursemap/__init__.py
discoursemap/main.py
discoursemap/quick_scan.py
discoursemap/analysis/__init__.py
discoursemap/analysis/endpoints/__init__.py
discoursemap/analysis/endpoints/endpoint_module.py
discoursemap/analysis/endpoints/endpoint_scanner.py
discoursemap/analysis/files/__init__.py
discoursemap/analysis/files/asset_file_checker.py
discoursemap/analysis/files/core_file_checker.py
discoursemap/analysis/files/file_integrity_module.py
discoursemap/analysis/files/malicious_pattern_checker.py
discoursemap/analysis/files/suspicious_file_scanner.py
discoursemap/analysis/files/theme_file_checker.py
discoursemap/analysis/info/__init__.py
discoursemap/analysis/info/info_module.py
discoursemap/analysis/passive/__init__.py
discoursemap/analysis/passive/passive_scanner_module.py
discoursemap/analysis/plugins/__init__.py
discoursemap/analysis/plugins/malicious_pattern_checker.py
discoursemap/analysis/plugins/plugin_bruteforce_module.py
discoursemap/analysis/plugins/plugin_detection_module.py
discoursemap/analysis/plugins/plugin_file_checker.py
discoursemap/analysis/plugins/plugin_module.py
discoursemap/analysis/plugins/plugin_signatures.py
discoursemap/analysis/plugins/plugin_vulnerabilities.py
discoursemap/compliance/__init__.py
discoursemap/compliance/compliance_module.py
discoursemap/compliance/gdpr_ccpa_tests.py
discoursemap/compliance/owasp_tests.py
discoursemap/core/__init__.py
discoursemap/core/banner.py
discoursemap/core/report_generator.py
discoursemap/core/reporter.py
discoursemap/core/scanner.py
discoursemap/discourse_specific/__init__.py
discoursemap/discourse_specific/http_utils.py
discoursemap/discourse_specific/admin/__init__.py
discoursemap/discourse_specific/admin/admin_module.py
discoursemap/discourse_specific/badges/__init__.py
discoursemap/discourse_specific/badges/badge_module.py
discoursemap/discourse_specific/cache/__init__.py
discoursemap/discourse_specific/cache/cache_module.py
discoursemap/discourse_specific/categories/__init__.py
discoursemap-2.0.5.dist-info/licenses/LICENSE
discoursemap-2.0.5.dist-info/METADATA
discoursemap-2.0.5.dist-info/WHEEL
discoursemap-2.0.5.dist-info/entry_points.txt
discoursemap-2.0.5.dist-info/top_level.txt
discoursemap-2.0.5.dist-info/RECORD
