Metadata-Version: 2.4
Name: discoursemap
Version: 2.0.5
Summary: Discourse forum security scanner. Written for security professionals and forum administrators.
Author-email: ibrahimsql <ibrahimsql@proton.me>
Maintainer-email: ibrahimsql <ibrahimsql@proton.me>
License: MIT
Project-URL: Homepage, https://github.com/ibrahmsql/discoursemap
Project-URL: Bug Reports, https://github.com/ibrahmsql/discoursemap/issues
Project-URL: Source, https://github.com/ibrahmsql/discoursemap
Project-URL: Documentation, https://github.com/ibrahmsql/discoursemap#readme
Keywords: discourse,security,scanner,penetration-testing,vulnerability-scanner,cybersecurity
Classifier: Development Status :: 4 - Beta
Classifier: Intended Audience :: Information Technology
Classifier: Topic :: Security
Classifier: Topic :: Internet :: WWW/HTTP :: Site Management
Classifier: License :: OSI Approved :: MIT License
Classifier: Programming Language :: Python :: 3
Classifier: Programming Language :: Python :: 3.8
Classifier: Programming Language :: Python :: 3.9
Classifier: Programming Language :: Python :: 3.10
Classifier: Programming Language :: Python :: 3.11
Classifier: Programming Language :: Python :: 3.12
Classifier: Operating System :: OS Independent
Classifier: Environment :: Console
Requires-Python: >=3.8
License-File: LICENSE
Requires-Dist: PyYAML==6.0.3
Requires-Dist: requests>=2.32.0
Requires-Dist: beautifulsoup4>=4.13.0
Requires-Dist: lxml>=6.0.0
Requires-Dist: colorama>=0.4.6
Requires-Dist: tqdm>=4.67.0
Requires-Dist: jinja2>=3.1.6
Requires-Dist: urllib3>=2.5.0
Requires-Dist: certifi>=2025.7.14
Requires-Dist: chardet>=5.2.0
Requires-Dist: idna>=3.10
Requires-Dist: pysocks>=1.7.1
Requires-Dist: cryptography>=45.0.0
Requires-Dist: pyopenssl>=25.1.0
Requires-Dist: typing-extensions>=4.0.0
Dynamic: license-file
